LICENSE
MANIFEST.in
README.rst
setup.py
dashing/__init__.py
dashing/permissions.py
dashing/settings.py
dashing/utils.py
dashing/views.py
dashing/widgets.py
dashing/static/dashing-config.js
dashing/static/dashing.css
dashing/static/dashing.js
dashing/static/utils.js
dashing/static/fonts/FontAwesome.otf
dashing/static/fonts/fontawesome-webfont.eot
dashing/static/fonts/fontawesome-webfont.svg
dashing/static/fonts/fontawesome-webfont.ttf
dashing/static/fonts/fontawesome-webfont.woff
dashing/static/libs/d3.js
dashing/static/libs/jquery-1.11.0.js
dashing/static/libs/jquery.knob.js
dashing/static/libs/moment-with-langs.js
dashing/static/libs/rivets.bundled.min.js
dashing/static/libs/font-awesome/font-awesome.css
dashing/static/libs/jquery-gridster/jquery.gridster.css
dashing/static/libs/jquery-gridster/jquery.gridster.js
dashing/static/libs/rickshaw/rickshaw.css
dashing/static/libs/rickshaw/rickshaw.js
dashing/static/widgets/clock/clock.css
dashing/static/widgets/clock/clock.html
dashing/static/widgets/clock/clock.js
dashing/static/widgets/graph/graph.css
dashing/static/widgets/graph/graph.html
dashing/static/widgets/graph/graph.js
dashing/static/widgets/list/list.css
dashing/static/widgets/list/list.html
dashing/static/widgets/list/list.js
dashing/static/widgets/number/number.css
dashing/static/widgets/number/number.html
dashing/static/widgets/number/number.js
dashing/templates/dashing/base.html
dashing/templates/dashing/dashboard.html
dashing/templatetags/__init__.py
dashing/templatetags/__init__.pyc
dashing/templatetags/dashing_resources.py
dashing/templatetags/dashing_resources.pyc
django_dashing_custom_torsten.egg-info/PKG-INFO
django_dashing_custom_torsten.egg-info/SOURCES.txt
django_dashing_custom_torsten.egg-info/dependency_links.txt
django_dashing_custom_torsten.egg-info/top_level.txt
docs/Makefile
docs/conf.py
docs/dashboards.rst
docs/getting-started.rst
docs/index.rst
docs/widgets.rst