Metadata-Version: 1.1
Name: django-dashing-custom-torsten
Version: 0.2.5b3
Summary: A simple Django dashboard app to visualize interesting data about your project. Custom for testing by Torsten Feld
Home-page: https://github.com/torstenfeld/django-dashing
Author: Torsten Feld (Original: Mauricio Reyes)
Author-email: torsten.feld@avira.com (Original: mreyes@talpor.com)
License: MIT License
Platform: UNKNOWN
Classifier: Development Status :: 3 - Alpha
Classifier: Environment :: Web Environment
Classifier: Framework :: Django
Classifier: Intended Audience :: Developers
Classifier: License :: OSI Approved :: MIT License
Classifier: Operating System :: OS Independent
Classifier: Programming Language :: Python
Classifier: Programming Language :: Python :: 2.7
Classifier: Topic :: Internet :: WWW/HTTP
Classifier: Topic :: Internet :: WWW/HTTP :: Dynamic Content
Classifier: Topic :: Software Development :: Libraries :: Python Modules
Classifier: Topic :: Software Development :: Localization
Classifier: Topic :: Utilities
